{
  "history": [
    {
      "timestamp": "2026-03-22T17:07:10.584825+00:00",
      "feed": "inflearn_conference",
      "status": "success",
      "count": 0,
      "message": "⚠️ 필터링된 영상 없음 - 빈 RSS 생성: docs/inflearn-conference.xml"
    },
    {
      "timestamp": "2026-03-23T17:19:52.209860+00:00",
      "feed": "velog_trending",
      "status": "success",
      "count": 30,
      "message": "docs/velog-trending.xml 생성 완료"
    },
    {
      "timestamp": "2026-03-23T17:19:52.827521+00:00",
      "feed": "naver_conference",
      "status": "success",
      "count": 0,
      "message": "⚠️ 필터링된 영상 없음 - 빈 RSS 생성: docs/naver-conference.xml"
    },
    {
      "timestamp": "2026-03-23T17:19:53.385767+00:00",
      "feed": "inflearn_conference",
      "status": "success",
      "count": 0,
      "message": "⚠️ 필터링된 영상 없음 - 빈 RSS 생성: docs/inflearn-conference.xml"
    },
    {
      "timestamp": "2026-03-24T17:22:40.671923+00:00",
      "feed": "velog_trending",
      "status": "success",
      "count": 30,
      "message": "docs/velog-trending.xml 생성 완료"
    },
    {
      "timestamp": "2026-03-24T17:22:41.021602+00:00",
      "feed": "naver_conference",
      "status": "success",
      "count": 0,
      "message": "⚠️ 필터링된 영상 없음 - 빈 RSS 생성: docs/naver-conference.xml"
    },
    {
      "timestamp": "2026-03-24T17:22:41.180223+00:00",
      "feed": "inflearn_conference",
      "status": "success",
      "count": 0,
      "message": "⚠️ 필터링된 영상 없음 - 빈 RSS 생성: docs/inflearn-conference.xml"
    },
    {
      "timestamp": "2026-03-25T17:24:06.509971+00:00",
      "feed": "velog_trending",
      "status": "success",
      "count": 30,
      "message": "docs/velog-trending.xml 생성 완료"
    },
    {
      "timestamp": "2026-03-25T17:24:07.339511+00:00",
      "feed": "naver_conference",
      "status": "success",
      "count": 0,
      "message": "⚠️ 필터링된 영상 없음 - 빈 RSS 생성: docs/naver-conference.xml"
    },
    {
      "timestamp": "2026-03-25T17:24:07.498795+00:00",
      "feed": "inflearn_conference",
      "status": "success",
      "count": 0,
      "message": "⚠️ 필터링된 영상 없음 - 빈 RSS 생성: docs/inflearn-conference.xml"
    },
    {
      "timestamp": "2026-03-26T17:25:04.228188+00:00",
      "feed": "velog_trending",
      "status": "success",
      "count": 30,
      "message": "docs/velog-trending.xml 생성 완료"
    },
    {
      "timestamp": "2026-03-26T17:25:04.466270+00:00",
      "feed": "naver_conference",
      "status": "success",
      "count": 0,
      "message": "⚠️ 필터링된 영상 없음 - 빈 RSS 생성: docs/naver-conference.xml"
    },
    {
      "timestamp": "2026-03-26T17:25:04.700824+00:00",
      "feed": "inflearn_conference",
      "status": "success",
      "count": 0,
      "message": "⚠️ 필터링된 영상 없음 - 빈 RSS 생성: docs/inflearn-conference.xml"
    },
    {
      "timestamp": "2026-03-27T17:19:54.751463+00:00",
      "feed": "velog_trending",
      "status": "success",
      "count": 30,
      "message": "docs/velog-trending.xml 생성 완료"
    },
    {
      "timestamp": "2026-03-27T17:19:55.123091+00:00",
      "feed": "naver_conference",
      "status": "success",
      "count": 0,
      "message": "⚠️ 필터링된 영상 없음 - 빈 RSS 생성: docs/naver-conference.xml"
    },
    {
      "timestamp": "2026-03-27T17:19:55.293586+00:00",
      "feed": "inflearn_conference",
      "status": "success",
      "count": 0,
      "message": "⚠️ 필터링된 영상 없음 - 빈 RSS 생성: docs/inflearn-conference.xml"
    },
    {
      "timestamp": "2026-03-28T17:09:26.810128+00:00",
      "feed": "velog_trending",
      "status": "success",
      "count": 30,
      "message": "docs/velog-trending.xml 생성 완료"
    },
    {
      "timestamp": "2026-03-28T17:09:27.096384+00:00",
      "feed": "naver_conference",
      "status": "success",
      "count": 0,
      "message": "⚠️ 필터링된 영상 없음 - 빈 RSS 생성: docs/naver-conference.xml"
    },
    {
      "timestamp": "2026-03-28T17:09:27.281411+00:00",
      "feed": "inflearn_conference",
      "status": "success",
      "count": 0,
      "message": "⚠️ 필터링된 영상 없음 - 빈 RSS 생성: docs/inflearn-conference.xml"
    },
    {
      "timestamp": "2026-03-29T17:10:13.795874+00:00",
      "feed": "velog_trending",
      "status": "success",
      "count": 30,
      "message": "docs/velog-trending.xml 생성 완료"
    },
    {
      "timestamp": "2026-03-29T17:10:14.012116+00:00",
      "feed": "naver_conference",
      "status": "success",
      "count": 0,
      "message": "⚠️ 필터링된 영상 없음 - 빈 RSS 생성: docs/naver-conference.xml"
    },
    {
      "timestamp": "2026-03-29T17:10:14.143977+00:00",
      "feed": "inflearn_conference",
      "status": "success",
      "count": 0,
      "message": "⚠️ 필터링된 영상 없음 - 빈 RSS 생성: docs/inflearn-conference.xml"
    },
    {
      "timestamp": "2026-03-30T17:20:42.287877+00:00",
      "feed": "velog_trending",
      "status": "success",
      "count": 30,
      "message": "docs/velog-trending.xml 생성 완료"
    },
    {
      "timestamp": "2026-03-30T17:20:42.730093+00:00",
      "feed": "naver_conference",
      "status": "success",
      "count": 0,
      "message": "⚠️ 필터링된 영상 없음 - 빈 RSS 생성: docs/naver-conference.xml"
    },
    {
      "timestamp": "2026-03-30T17:20:42.967742+00:00",
      "feed": "inflearn_conference",
      "status": "success",
      "count": 0,
      "message": "⚠️ 필터링된 영상 없음 - 빈 RSS 생성: docs/inflearn-conference.xml"
    },
    {
      "timestamp": "2026-03-31T17:23:00.416202+00:00",
      "feed": "velog_trending",
      "status": "success",
      "count": 30,
      "message": "docs/velog-trending.xml 생성 완료"
    },
    {
      "timestamp": "2026-03-31T17:23:00.702562+00:00",
      "feed": "naver_conference",
      "status": "success",
      "count": 0,
      "message": "⚠️ 필터링된 영상 없음 - 빈 RSS 생성: docs/naver-conference.xml"
    },
    {
      "timestamp": "2026-03-31T17:23:01.036804+00:00",
      "feed": "inflearn_conference",
      "status": "success",
      "count": 0,
      "message": "⚠️ 필터링된 영상 없음 - 빈 RSS 생성: docs/inflearn-conference.xml"
    },
    {
      "timestamp": "2026-04-01T17:20:51.292355+00:00",
      "feed": "velog_trending",
      "status": "success",
      "count": 30,
      "message": "docs/velog-trending.xml 생성 완료"
    },
    {
      "timestamp": "2026-04-01T17:20:51.562824+00:00",
      "feed": "naver_conference",
      "status": "success",
      "count": 0,
      "message": "⚠️ 필터링된 영상 없음 - 빈 RSS 생성: docs/naver-conference.xml"
    },
    {
      "timestamp": "2026-04-01T17:20:51.810249+00:00",
      "feed": "inflearn_conference",
      "status": "success",
      "count": 0,
      "message": "⚠️ 필터링된 영상 없음 - 빈 RSS 생성: docs/inflearn-conference.xml"
    },
    {
      "timestamp": "2026-04-02T17:19:28.668498+00:00",
      "feed": "velog_trending",
      "status": "success",
      "count": 30,
      "message": "docs/velog-trending.xml 생성 완료"
    },
    {
      "timestamp": "2026-04-02T17:19:28.918187+00:00",
      "feed": "naver_conference",
      "status": "success",
      "count": 0,
      "message": "⚠️ 필터링된 영상 없음 - 빈 RSS 생성: docs/naver-conference.xml"
    },
    {
      "timestamp": "2026-04-02T17:19:29.065448+00:00",
      "feed": "inflearn_conference",
      "status": "success",
      "count": 0,
      "message": "⚠️ 필터링된 영상 없음 - 빈 RSS 생성: docs/inflearn-conference.xml"
    },
    {
      "timestamp": "2026-04-03T17:12:28.920317+00:00",
      "feed": "velog_trending",
      "status": "success",
      "count": 30,
      "message": "docs/velog-trending.xml 생성 완료"
    },
    {
      "timestamp": "2026-04-03T17:12:29.219562+00:00",
      "feed": "naver_conference",
      "status": "success",
      "count": 0,
      "message": "⚠️ 필터링된 영상 없음 - 빈 RSS 생성: docs/naver-conference.xml"
    },
    {
      "timestamp": "2026-04-03T17:12:29.320564+00:00",
      "feed": "inflearn_conference",
      "status": "success",
      "count": 0,
      "message": "⚠️ 필터링된 영상 없음 - 빈 RSS 생성: docs/inflearn-conference.xml"
    },
    {
      "timestamp": "2026-04-04T17:10:48.110733+00:00",
      "feed": "velog_trending",
      "status": "success",
      "count": 30,
      "message": "docs/velog-trending.xml 생성 완료"
    },
    {
      "timestamp": "2026-04-04T17:10:48.367010+00:00",
      "feed": "naver_conference",
      "status": "success",
      "count": 0,
      "message": "⚠️ 필터링된 영상 없음 - 빈 RSS 생성: docs/naver-conference.xml"
    },
    {
      "timestamp": "2026-04-04T17:10:48.486394+00:00",
      "feed": "inflearn_conference",
      "status": "success",
      "count": 0,
      "message": "⚠️ 필터링된 영상 없음 - 빈 RSS 생성: docs/inflearn-conference.xml"
    },
    {
      "timestamp": "2026-04-05T17:10:55.076088+00:00",
      "feed": "velog_trending",
      "status": "success",
      "count": 30,
      "message": "docs/velog-trending.xml 생성 완료"
    },
    {
      "timestamp": "2026-04-05T17:10:55.338527+00:00",
      "feed": "naver_conference",
      "status": "success",
      "count": 0,
      "message": "⚠️ 필터링된 영상 없음 - 빈 RSS 생성: docs/naver-conference.xml"
    },
    {
      "timestamp": "2026-04-05T17:10:55.589406+00:00",
      "feed": "inflearn_conference",
      "status": "success",
      "count": 0,
      "message": "⚠️ 필터링된 영상 없음 - 빈 RSS 생성: docs/inflearn-conference.xml"
    },
    {
      "timestamp": "2026-04-06T17:18:55.960425+00:00",
      "feed": "velog_trending",
      "status": "success",
      "count": 30,
      "message": "docs/velog-trending.xml 생성 완료"
    },
    {
      "timestamp": "2026-04-06T17:18:56.522014+00:00",
      "feed": "naver_conference",
      "status": "success",
      "count": 0,
      "message": "⚠️ 필터링된 영상 없음 - 빈 RSS 생성: docs/naver-conference.xml"
    },
    {
      "timestamp": "2026-04-06T17:18:56.986864+00:00",
      "feed": "inflearn_conference",
      "status": "success",
      "count": 0,
      "message": "⚠️ 필터링된 영상 없음 - 빈 RSS 생성: docs/inflearn-conference.xml"
    },
    {
      "timestamp": "2026-04-07T17:23:16.152976+00:00",
      "feed": "velog_trending",
      "status": "success",
      "count": 30,
      "message": "docs/velog-trending.xml 생성 완료"
    },
    {
      "timestamp": "2026-04-07T17:23:16.370274+00:00",
      "feed": "naver_conference",
      "status": "success",
      "count": 0,
      "message": "⚠️ 필터링된 영상 없음 - 빈 RSS 생성: docs/naver-conference.xml"
    },
    {
      "timestamp": "2026-04-07T17:23:16.514469+00:00",
      "feed": "inflearn_conference",
      "status": "success",
      "count": 0,
      "message": "⚠️ 필터링된 영상 없음 - 빈 RSS 생성: docs/inflearn-conference.xml"
    },
    {
      "timestamp": "2026-04-08T17:29:58.066259+00:00",
      "feed": "velog_trending",
      "status": "success",
      "count": 30,
      "message": "docs/velog-trending.xml 생성 완료"
    },
    {
      "timestamp": "2026-04-08T17:29:58.327773+00:00",
      "feed": "naver_conference",
      "status": "success",
      "count": 0,
      "message": "⚠️ 필터링된 영상 없음 - 빈 RSS 생성: docs/naver-conference.xml"
    },
    {
      "timestamp": "2026-04-08T17:29:58.459314+00:00",
      "feed": "inflearn_conference",
      "status": "success",
      "count": 0,
      "message": "⚠️ 필터링된 영상 없음 - 빈 RSS 생성: docs/inflearn-conference.xml"
    },
    {
      "timestamp": "2026-04-09T17:26:54.275959+00:00",
      "feed": "velog_trending",
      "status": "success",
      "count": 30,
      "message": "docs/velog-trending.xml 생성 완료"
    },
    {
      "timestamp": "2026-04-09T17:26:54.566509+00:00",
      "feed": "naver_conference",
      "status": "success",
      "count": 0,
      "message": "⚠️ 필터링된 영상 없음 - 빈 RSS 생성: docs/naver-conference.xml"
    },
    {
      "timestamp": "2026-04-09T17:26:54.721623+00:00",
      "feed": "inflearn_conference",
      "status": "success",
      "count": 0,
      "message": "⚠️ 필터링된 영상 없음 - 빈 RSS 생성: docs/inflearn-conference.xml"
    },
    {
      "timestamp": "2026-04-10T17:18:35.626554+00:00",
      "feed": "velog_trending",
      "status": "success",
      "count": 30,
      "message": "docs/velog-trending.xml 생성 완료"
    },
    {
      "timestamp": "2026-04-10T17:18:36.049397+00:00",
      "feed": "naver_conference",
      "status": "success",
      "count": 0,
      "message": "⚠️ 필터링된 영상 없음 - 빈 RSS 생성: docs/naver-conference.xml"
    },
    {
      "timestamp": "2026-04-10T17:18:36.263565+00:00",
      "feed": "inflearn_conference",
      "status": "success",
      "count": 0,
      "message": "⚠️ 필터링된 영상 없음 - 빈 RSS 생성: docs/inflearn-conference.xml"
    },
    {
      "timestamp": "2026-04-11T17:11:37.292313+00:00",
      "feed": "velog_trending",
      "status": "success",
      "count": 30,
      "message": "docs/velog-trending.xml 생성 완료"
    },
    {
      "timestamp": "2026-04-11T17:11:37.658416+00:00",
      "feed": "naver_conference",
      "status": "success",
      "count": 0,
      "message": "⚠️ 필터링된 영상 없음 - 빈 RSS 생성: docs/naver-conference.xml"
    },
    {
      "timestamp": "2026-04-11T17:11:37.919991+00:00",
      "feed": "inflearn_conference",
      "status": "success",
      "count": 0,
      "message": "⚠️ 필터링된 영상 없음 - 빈 RSS 생성: docs/inflearn-conference.xml"
    },
    {
      "timestamp": "2026-04-12T17:12:28.411570+00:00",
      "feed": "velog_trending",
      "status": "success",
      "count": 30,
      "message": "docs/velog-trending.xml 생성 완료"
    },
    {
      "timestamp": "2026-04-12T17:12:28.844668+00:00",
      "feed": "naver_conference",
      "status": "success",
      "count": 0,
      "message": "⚠️ 필터링된 영상 없음 - 빈 RSS 생성: docs/naver-conference.xml"
    },
    {
      "timestamp": "2026-04-12T17:12:28.989099+00:00",
      "feed": "inflearn_conference",
      "status": "success",
      "count": 0,
      "message": "⚠️ 필터링된 영상 없음 - 빈 RSS 생성: docs/inflearn-conference.xml"
    },
    {
      "timestamp": "2026-04-13T17:25:21.771694+00:00",
      "feed": "velog_trending",
      "status": "success",
      "count": 30,
      "message": "docs/velog-trending.xml 생성 완료"
    },
    {
      "timestamp": "2026-04-13T17:25:21.967995+00:00",
      "feed": "naver_conference",
      "status": "success",
      "count": 0,
      "message": "⚠️ 필터링된 영상 없음 - 빈 RSS 생성: docs/naver-conference.xml"
    },
    {
      "timestamp": "2026-04-13T17:25:22.199052+00:00",
      "feed": "inflearn_conference",
      "status": "success",
      "count": 0,
      "message": "⚠️ 필터링된 영상 없음 - 빈 RSS 생성: docs/inflearn-conference.xml"
    },
    {
      "timestamp": "2026-04-14T17:27:28.196000+00:00",
      "feed": "velog_trending",
      "status": "success",
      "count": 30,
      "message": "docs/velog-trending.xml 생성 완료"
    },
    {
      "timestamp": "2026-04-14T17:27:28.493281+00:00",
      "feed": "naver_conference",
      "status": "success",
      "count": 0,
      "message": "⚠️ 필터링된 영상 없음 - 빈 RSS 생성: docs/naver-conference.xml"
    },
    {
      "timestamp": "2026-04-14T17:27:28.675524+00:00",
      "feed": "inflearn_conference",
      "status": "success",
      "count": 0,
      "message": "⚠️ 필터링된 영상 없음 - 빈 RSS 생성: docs/inflearn-conference.xml"
    },
    {
      "timestamp": "2026-04-15T17:25:53.471635+00:00",
      "feed": "velog_trending",
      "status": "success",
      "count": 30,
      "message": "docs/velog-trending.xml 생성 완료"
    },
    {
      "timestamp": "2026-04-15T17:25:53.757258+00:00",
      "feed": "naver_conference",
      "status": "success",
      "count": 0,
      "message": "⚠️ 필터링된 영상 없음 - 빈 RSS 생성: docs/naver-conference.xml"
    },
    {
      "timestamp": "2026-04-15T17:25:53.916975+00:00",
      "feed": "inflearn_conference",
      "status": "success",
      "count": 0,
      "message": "⚠️ 필터링된 영상 없음 - 빈 RSS 생성: docs/inflearn-conference.xml"
    },
    {
      "timestamp": "2026-04-16T17:31:16.997363+00:00",
      "feed": "velog_trending",
      "status": "success",
      "count": 30,
      "message": "docs/velog-trending.xml 생성 완료"
    },
    {
      "timestamp": "2026-04-16T17:31:18.036067+00:00",
      "feed": "naver_conference",
      "status": "success",
      "count": 0,
      "message": "⚠️ 필터링된 영상 없음 - 빈 RSS 생성: docs/naver-conference.xml"
    },
    {
      "timestamp": "2026-04-16T17:31:18.235214+00:00",
      "feed": "inflearn_conference",
      "status": "success",
      "count": 0,
      "message": "⚠️ 필터링된 영상 없음 - 빈 RSS 생성: docs/inflearn-conference.xml"
    },
    {
      "timestamp": "2026-04-17T17:19:14.929195+00:00",
      "feed": "velog_trending",
      "status": "success",
      "count": 30,
      "message": "docs/velog-trending.xml 생성 완료"
    },
    {
      "timestamp": "2026-04-17T17:19:15.758651+00:00",
      "feed": "naver_conference",
      "status": "success",
      "count": 0,
      "message": "⚠️ 필터링된 영상 없음 - 빈 RSS 생성: docs/naver-conference.xml"
    },
    {
      "timestamp": "2026-04-17T17:19:15.898066+00:00",
      "feed": "inflearn_conference",
      "status": "success",
      "count": 0,
      "message": "⚠️ 필터링된 영상 없음 - 빈 RSS 생성: docs/inflearn-conference.xml"
    },
    {
      "timestamp": "2026-04-18T17:13:43.013105+00:00",
      "feed": "velog_trending",
      "status": "success",
      "count": 30,
      "message": "docs/velog-trending.xml 생성 완료"
    },
    {
      "timestamp": "2026-04-18T17:13:43.327918+00:00",
      "feed": "naver_conference",
      "status": "success",
      "count": 0,
      "message": "⚠️ 필터링된 영상 없음 - 빈 RSS 생성: docs/naver-conference.xml"
    },
    {
      "timestamp": "2026-04-18T17:13:43.484164+00:00",
      "feed": "inflearn_conference",
      "status": "success",
      "count": 0,
      "message": "⚠️ 필터링된 영상 없음 - 빈 RSS 생성: docs/inflearn-conference.xml"
    },
    {
      "timestamp": "2026-04-19T17:13:42.209549+00:00",
      "feed": "velog_trending",
      "status": "success",
      "count": 30,
      "message": "docs/velog-trending.xml 생성 완료"
    },
    {
      "timestamp": "2026-04-19T17:13:42.601269+00:00",
      "feed": "naver_conference",
      "status": "success",
      "count": 0,
      "message": "⚠️ 필터링된 영상 없음 - 빈 RSS 생성: docs/naver-conference.xml"
    },
    {
      "timestamp": "2026-04-19T17:13:42.852698+00:00",
      "feed": "inflearn_conference",
      "status": "success",
      "count": 0,
      "message": "⚠️ 필터링된 영상 없음 - 빈 RSS 생성: docs/inflearn-conference.xml"
    },
    {
      "timestamp": "2026-04-20T17:24:44.964557+00:00",
      "feed": "velog_trending",
      "status": "success",
      "count": 30,
      "message": "docs/velog-trending.xml 생성 완료"
    },
    {
      "timestamp": "2026-04-20T17:24:45.439149+00:00",
      "feed": "naver_conference",
      "status": "success",
      "count": 0,
      "message": "⚠️ 필터링된 영상 없음 - 빈 RSS 생성: docs/naver-conference.xml"
    },
    {
      "timestamp": "2026-04-20T17:24:45.948581+00:00",
      "feed": "inflearn_conference",
      "status": "success",
      "count": 0,
      "message": "⚠️ 필터링된 영상 없음 - 빈 RSS 생성: docs/inflearn-conference.xml"
    },
    {
      "timestamp": "2026-04-21T17:24:09.188987+00:00",
      "feed": "velog_trending",
      "status": "success",
      "count": 30,
      "message": "docs/velog-trending.xml 생성 완료"
    },
    {
      "timestamp": "2026-04-21T17:24:10.000302+00:00",
      "feed": "naver_conference",
      "status": "success",
      "count": 0,
      "message": "⚠️ 필터링된 영상 없음 - 빈 RSS 생성: docs/naver-conference.xml"
    },
    {
      "timestamp": "2026-04-21T17:24:10.176722+00:00",
      "feed": "inflearn_conference",
      "status": "success",
      "count": 0,
      "message": "⚠️ 필터링된 영상 없음 - 빈 RSS 생성: docs/inflearn-conference.xml"
    },
    {
      "timestamp": "2026-04-22T17:22:52.280458+00:00",
      "feed": "velog_trending",
      "status": "success",
      "count": 30,
      "message": "docs/velog-trending.xml 생성 완료"
    },
    {
      "timestamp": "2026-04-22T17:22:52.504111+00:00",
      "feed": "naver_conference",
      "status": "success",
      "count": 0,
      "message": "⚠️ 필터링된 영상 없음 - 빈 RSS 생성: docs/naver-conference.xml"
    },
    {
      "timestamp": "2026-04-22T17:22:52.638404+00:00",
      "feed": "inflearn_conference",
      "status": "success",
      "count": 0,
      "message": "⚠️ 필터링된 영상 없음 - 빈 RSS 생성: docs/inflearn-conference.xml"
    },
    {
      "timestamp": "2026-04-23T17:32:45.507255+00:00",
      "feed": "velog_trending",
      "status": "success",
      "count": 30,
      "message": "docs/velog-trending.xml 생성 완료"
    },
    {
      "timestamp": "2026-04-23T17:32:45.780602+00:00",
      "feed": "naver_conference",
      "status": "success",
      "count": 0,
      "message": "⚠️ 필터링된 영상 없음 - 빈 RSS 생성: docs/naver-conference.xml"
    },
    {
      "timestamp": "2026-04-23T17:32:45.951794+00:00",
      "feed": "inflearn_conference",
      "status": "success",
      "count": 0,
      "message": "⚠️ 필터링된 영상 없음 - 빈 RSS 생성: docs/inflearn-conference.xml"
    },
    {
      "timestamp": "2026-04-24T17:21:31.209906+00:00",
      "feed": "velog_trending",
      "status": "success",
      "count": 30,
      "message": "docs/velog-trending.xml 생성 완료"
    },
    {
      "timestamp": "2026-04-24T17:21:31.472654+00:00",
      "feed": "naver_conference",
      "status": "success",
      "count": 0,
      "message": "⚠️ 필터링된 영상 없음 - 빈 RSS 생성: docs/naver-conference.xml"
    },
    {
      "timestamp": "2026-04-24T17:21:31.609133+00:00",
      "feed": "inflearn_conference",
      "status": "success",
      "count": 0,
      "message": "⚠️ 필터링된 영상 없음 - 빈 RSS 생성: docs/inflearn-conference.xml"
    }
  ]
}